CHANGES.txt
DEPENDENCES.txt
README.txt
setup.py
src/ng/__init__.py
src/ng.skin.ultor.egg-info/PKG-INFO
src/ng.skin.ultor.egg-info/SOURCES.txt
src/ng.skin.ultor.egg-info/dependency_links.txt
src/ng.skin.ultor.egg-info/namespace_packages.txt
src/ng.skin.ultor.egg-info/not-zip-safe
src/ng.skin.ultor.egg-info/requires.txt
src/ng.skin.ultor.egg-info/top_level.txt
src/ng/skin/__init__.py
src/ng/skin/ultor/__init__.py
src/ng/skin/ultor/configure.zcml
src/ng/skin/ultor/interfaces.py
src/ng/skin/ultor/ng.skin.ultor.txt
src/ng/skin/ultor/orderinformation.py
src/ng/skin/ultor/skeleton.pt
src/ng/skin/ultor/style.css
src/ng/skin/ultor/style_form.css
src/ng/skin/ultor/style_ie.css
src/ng/skin/ultor/style_print.css
src/ng/skin/ultor/etc/ng.skin.ultor-configure.zcml
src/ng/skin/ultor/images/bottomlogo.png
src/ng/skin/ultor/images/favicon.ico
src/ng/skin/ultor/images/logo.gif
src/ng/skin/ultor/images/toplogo.png
src/ng/skin/ultor/page/__init__.py
src/ng/skin/ultor/page/configure.zcml
src/ng/skin/ultor/page/blog/__init__.py
src/ng/skin/ultor/page/blog/blog.css
src/ng/skin/ultor/page/blog/blog.pt
src/ng/skin/ultor/page/blog/blog.py
src/ng/skin/ultor/page/blog/configure.zcml
src/ng/skin/ultor/page/commonedit/__init__.py
src/ng/skin/ultor/page/commonedit/configure.zcml
src/ng/skin/ultor/page/contentlet/__init__.py
src/ng/skin/ultor/page/contentlet/configure.zcml
src/ng/skin/ultor/page/main/__init__.py
src/ng/skin/ultor/page/main/configure.zcml
src/ng/skin/ultor/page/main/main.css
src/ng/skin/ultor/viewlet/__init__.py
src/ng/skin/ultor/viewlet/configure.zcml
src/ng/skin/ultor/viewlet/interfaces.py
src/ng/skin/ultor/viewlet/viewletcolumn.pt